LICENSE
MANIFEST.in
README.rst
requirements.txt
setup.py
metabolabpy/__init__.py
metabolabpy.egg-info/PKG-INFO
metabolabpy.egg-info/SOURCES.txt
metabolabpy.egg-info/dependency_links.txt
metabolabpy.egg-info/requires.txt
metabolabpy.egg-info/top_level.txt
metabolabpy/GUI/__init__.py
metabolabpy/GUI/phCorr.py
metabolabpy/exampleScripts/adaptiveLineBroadening.py
metabolabpy/exampleScripts/example1DScript.py
metabolabpy/exampleScripts/example2DHSQCScript.py
metabolabpy/exampleScripts/example2DJresScript.py
metabolabpy/exampleScripts/example2DNMRPipeScript.py
metabolabpy/exampleScripts/exampleAutoBaselineScript.py
metabolabpy/exampleScripts/exampleAutoPhaseScript.py
metabolabpy/exampleScripts/exampleIsotopomerAnalysisScript.py
metabolabpy/exampleScripts/examplePreprocessingScript.py
metabolabpy/icon/Browse.plb
metabolabpy/icon/ia.png
metabolabpy/icon/icon-16.png
metabolabpy/icon/icon-24.png
metabolabpy/icon/icon-256.png
metabolabpy/icon/icon-32.png
metabolabpy/icon/icon-48.png
metabolabpy/icon/icon.ico
metabolabpy/icon/iconiso-16.png
metabolabpy/icon/iconiso-24.png
metabolabpy/icon/iconiso-256.png
metabolabpy/icon/iconiso-32.png
metabolabpy/icon/iconiso-48.png
metabolabpy/icon/metabolab_icon.png
metabolabpy/icon/metabolab_icon2.png
metabolabpy/icon/pymetabolab_icon_128.png
metabolabpy/icon/pymetabolab_icon_64.png
metabolabpy/nmr/.DS_Store
metabolabpy/nmr/acqPars.py
metabolabpy/nmr/acqProcparRegEx.py
metabolabpy/nmr/acqRegEx.py
metabolabpy/nmr/apcbc.py
metabolabpy/nmr/dispPars.py
metabolabpy/nmr/hsqcData.py
metabolabpy/nmr/nmr1dData.py
metabolabpy/nmr/nmr1dSim.py
metabolabpy/nmr/nmrConfig.py
metabolabpy/nmr/nmrData.py
metabolabpy/nmr/nmrDataSet.py
metabolabpy/nmr/nmrHsqc.py
metabolabpy/nmr/nmrPreProc.py
metabolabpy/nmr/nmrpipeData.py
metabolabpy/nmr/phase3.py
metabolabpy/nmr/procPars.py
metabolabpy/nmr/procProcparRegEx.py
metabolabpy/nmr/procRegEx.py
metabolabpy/nmr/splineBaseline.py
metabolabpy/nmr/jupyter/gcmsData.xlsx
metabolabpy/nmr/jupyter/hsqcData.xlsx
metabolabpy/nmr/jupyter/mlpy_1d_spc.ipynb
metabolabpy/nmr/jupyter/mlpy_2d_spc.ipynb
metabolabpy/nmr/jupyter/mlpy_2d_spc_ica.ipynb
metabolabpy/nmr/jupyter/nmr1dData.xlsx
