Metadata-Version: 2.2
Name: metabolabpy
Version: 0.9.85
Summary: Python package for data processing of NMR 1D and 2D metabolomics and metabolism tracing data
Home-page: https://github.com/ludwigc/metabolabpy
Author: Christian Ludwig
Author-email: C.Ludwig@bham.ac.uk 
License: GPLv3
Keywords: Metabolomics,Tracing,NMR,Data Processing,13C
Platform: MacOS, Windows, UNIX
Classifier: Programming Language :: Python :: 3
Classifier: Programming Language :: Python :: 3.9
Classifier: Topic :: Scientific/Engineering :: Bio-Informatics
Classifier: Topic :: Scientific/Engineering :: Chemistry
Classifier: Topic :: Utilities
Classifier: License :: OSI Approved :: GNU General Public License v3 (GPLv3)
Classifier: Operating System :: OS Independent
License-File: LICENSE
Requires-Dist: numpy
Requires-Dist: scipy
Requires-Dist: matplotlib
Requires-Dist: pandas
Requires-Dist: numba
Requires-Dist: scikit-learn
Requires-Dist: openpyxl
Requires-Dist: xlsxwriter
Requires-Dist: multiprocess
Requires-Dist: pybaselines
Requires-Dist: darkdetect
Requires-Dist: pywavelets
Requires-Dist: pygamma
Requires-Dist: mat73
Dynamic: author
Dynamic: author-email
Dynamic: classifier
Dynamic: description
Dynamic: home-page
Dynamic: keywords
Dynamic: license
Dynamic: platform
Dynamic: requires-dist
Dynamic: summary
